tronapi/__init__.py
tronapi/constants.py
tronapi/contract.py
tronapi/exceptions.py
tronapi/main.py
tronapi/manager.py
tronapi/module.py
tronapi/transactionbuilder.py
tronapi/trx.py
tronapi/common/__init__.py
tronapi/common/abi.py
tronapi/common/account.py
tronapi/common/blocks.py
tronapi/common/contracts.py
tronapi/common/datastructures.py
tronapi/common/datatypes.py
tronapi/common/encoding.py
tronapi/common/formatters.py
tronapi/common/normalizers.py
tronapi/common/threads.py
tronapi/common/transactions.py
tronapi/common/validation.py
tronapi/common/toolz/__init__.py
tronapi/providers/__init__.py
tronapi/providers/base.py
tronapi/providers/http.py
tronweb-3.1.5.1.dist-info/LICENSE
tronweb-3.1.5.1.dist-info/METADATA
tronweb-3.1.5.1.dist-info/WHEEL
tronweb-3.1.5.1.dist-info/top_level.txt
tronweb-3.1.5.1.dist-info/RECORD
